MANIFEST.in
README.txt
setup.cfg
setup.py
docs/HISTORY.txt
docs/LICENSE.GPL
docs/LICENSE.txt
gomobile/__init__.py
gomobile.imageinfo.egg-info/PKG-INFO
gomobile.imageinfo.egg-info/SOURCES.txt
gomobile.imageinfo.egg-info/dependency_links.txt
gomobile.imageinfo.egg-info/entry_points.txt
gomobile.imageinfo.egg-info/namespace_packages.txt
gomobile.imageinfo.egg-info/not-zip-safe
gomobile.imageinfo.egg-info/requires.txt
gomobile.imageinfo.egg-info/top_level.txt
gomobile/imageinfo/__init__.py
gomobile/imageinfo/configure.zcml
gomobile/imageinfo/interfaces.py
gomobile/imageinfo/utilities.py
gomobile/imageinfo/tests/__init__.py
gomobile/imageinfo/tests/base.py
gomobile/imageinfo/tests/logo.jpg
gomobile/imageinfo/tests/test_image_info.py
gomobile/imageinfo/tests/test_resize_remote.py