Metadata-Version: 1.1
Name: gomobile.imageinfo
Version: 0.9.3
Summary: Extract and manipulate different Zope image objects
Home-page: http://webandmobile.mfabrik.com
Author: mFabrik Rearch Oy
Author-email: research@mfabrik.com
License: GPL
Keywords: zope image resize pil plone
Platform: UNKNOWN
Classifier: Programming Language :: Python
Classifier: Topic :: Software Development :: Libraries :: Python Modules
Classifier: License :: OSI Approved :: GNU General Public License (GPL)
Classifier: Framework :: Plone
Classifier: Intended Audience :: Developers
